Metadata-Version: 2.1
Name: telethon-patch
Version: 0.1
Summary: UNKNOWN
Home-page: https://github.com/New-dev0/Telethon-Patch
Author: New-Dev0
Author-email: New-dev0@outlook.com
License: GNUV3
Keywords: telethon,telethon-patch,telegram,mtproto
Platform: UNKNOWN
Classifier: Programming Language :: Python :: 3
Classifier: Programming Language :: Python :: 3.8
Classifier: Programming Language :: Python :: 3.9
Classifier: Programming Language :: Python :: 3.10
Classifier: License :: OSI Approved :: GNU General Public License v3 (GPLv3)
Classifier: Operating System :: OS Independent
License-File: LICENSE
